[
  {
    "article_id": 1,
    "company_1": "Sayona Mining",
    "company_1_ticker": [],
    "company_2": "Piedmont Lithium",
    "company_2_ticker": null,
    "merged_entity": "Elevra Lithium",
    "deal_amount": null,
    "deal_currency": "Unknown",
    "article_type": "merger"
  },
  {
    "article_id": 2,
    "parent_company": "Newcrest Mining",
    "parent_company_ticker": null,
    "child_company": "Pretium Resources",
    "child_company_ticker": null,
    "deal_amount": "3.5 billion",
    "deal_currency": "CAD",
    "article_type": "acquisition"
  },
  {
    "article_id": 3,
    "article_type": "other"
  },
  {
    "article_id": 4,
    "company_1": "Karora Resources",
    "company_1_ticker": [],
    "company_2": "Westgold",
    "company_2_ticker": [],
    "merged_entity": null,
    "deal_amount": "3.4 billion",
    "deal_currency": "USD",
    "article_type": "merger"
  },
  {
    "article_id": 5,
    "parent_company": "Ramelius Resources",
    "parent_company_ticker": [],
    "child_company": "Spartan Resources",
    "child_company_ticker": [],
    "deal_amount": "2.4 billion",
    "deal_currency": "USD",
    "article_type": "acquisition"
  },
  {
    "article_id": 6,
    "parent_company": "Northern Star Resources",
    "parent_company_ticker": [],
    "child_company": "De Grey Mining",
    "child_company_ticker": [],
    "deal_amount": "5 billion",
    "deal_currency": "USD",
    "article_type": "acquisition"
  },
  {
    "article_id": 7,
    "parent_company": "Rio Tinto",
    "parent_company_ticker": null,
    "child_company": "Arcadium Lithium",
    "child_company_ticker": [
      "ASX",
      "New York Stock Exchange"
    ],
    "deal_amount": "6.7 billion",
    "deal_currency": "USD",
    "article_type": "acquisition"
  },
  {
    "article_id": 8,
    "article_type": "other"
  },
  {
    "article_id": 9,
    "company_1": "Equinox Gold",
    "company_1_ticker": [
      "TSX: EQX",
      "NYSE-A: EQX"
    ],
    "company_2": "Calibre Mining",
    "company_2_ticker": [
      "TSX: CXB"
    ],
    "merged_entity": "Equinox Gold",
    "deal_amount": "$2.56 billion",
    "deal_currency": "USD",
    "article_type": "merger"
  },
  {
    "article_id": 10,
    "parent_company": "Newmont",
    "parent_company_ticker": [],
    "child_company": "Newcrest Mining Limited",
    "child_company_ticker": null,
    "deal_amount": null,
    "deal_currency": "Unknown",
    "article_type": "acquisition"
  },
  {
    "article_id": 11,
    "parent_company": "Pilbara Minerals",
    "parent_company_ticker": [
      "ASX:PLS"
    ],
    "child_company": "Latin Resources",
    "child_company_ticker": [
      "ASX:LRS"
    ],
    "deal_amount": null,
    "deal_currency": "Unknown",
    "article_type": "acquisition"
  },
  {
    "article_id": 12,
    "company_1": "Rock Tech Lithium",
    "company_1_ticker": [],
    "company_2": "Arcore",
    "company_2_ticker": [],
    "merged_entity": "NewCo",
    "deal_amount": null,
    "deal_currency": "Unknown",
    "article_type": "merger"
  },
  {
    "article_id": 13,
    "parent_company": "Titanium Corp",
    "parent_company_ticker": ["TSX: TCP"],
    "child_company": "Azure Mining",
    "child_company_ticker": ["TSX: AZM", "NYSE-A: AZZ"],
    "deal_amount": "4.2 billion",
    "deal_currency": "CAD",
    "article_type": "acquisition"
  },
  {
    "article_id": 14,
    "company_1": "Phoenix Resources",
    "company_1_ticker": null,
    "company_2": "Quantum Mining",
    "company_2_ticker": null,
    "merged_entity": "Phoenix Resources",
    "deal_amount": "2.8 billion",
    "deal_currency": "AUD",
    "article_type": "merger"
  },
  {
    "article_id": 15,
    "article_type": "other"
  },
  {
    "article_id": 16,
    "article_type": "other"
  },
  {
    "article_id": 17,
    "parent_company": "European Wave Mining",
    "parent_company_ticker": null,
    "child_company": "Silverstone Resources",
    "child_company_ticker": null,
    "deal_amount": "3.6 billion",
    "deal_currency": "CAD",
    "article_type": "acquisition"
  },
  {
    "article_id": 18,
    "company_1": "Copper Valley Mining",
    "company_1_ticker": ["NYSE-A: CVMI"],
    "company_2": "Mountain Ridge Resources",
    "company_2_ticker": ["NYSE-A: MORR"],
    "merged_entity": "Valley Ridge Mining",
    "deal_amount": "1.5 billion",
    "deal_currency": "USD",
    "article_type": "merger"
  },
  {
    "article_id": 19,
    "parent_company": "Global Resources Corporation",
    "parent_company_ticker": null,
    "child_company": "Frontier Mining Limited",
    "child_company_ticker": null,
    "deal_amount": "920 million",
    "deal_currency": "USD",
    "article_type": "acquisition"
  },
  {
    "article_id": 20,
    "company_1": "Atlas Mining Corporation",
    "company_1_ticker": null,
    "company_2": "Pacific Metals",
    "company_2_ticker": null,
    "merged_entity": "Atlas Pacific Mining",
    "deal_amount": "3.1 billion",
    "deal_currency": "USD",
    "article_type": "merger"
  },
  {
    "article_id": 21,
    "article_type": "other"
  },
  {
    "article_id": 22,
    "parent_company": "Dynasty Mining",
    "parent_company_ticker": [],
    "child_company": "Explorer Resources",
    "child_company_ticker": [],
    "deal_amount": "1.8 billion",
    "deal_currency": "AUD",
    "article_type": "acquisition"
  }
]